{
  "single": {
    "basis": {
      "irrep_labels": [
        "GM1",
        "GM2",
        "GM3GM4",
        "(M)Z1",
        "(M)Z2",
        "(M)Z3Z4",
        "(N)L1",
        "(P)H1",
        "(PA)HA1",
        "(X)Y1",
        "(XA)T1"
      ],
      "degeneracies": [
        1,
        1,
        2,
        1,
        1,
        2,
        1,
        2,
        2,
        2,
        2
      ]
    },
    "ebrs": [
      {
        "wyckoff_position": "4a(4',2)",
        "ebr_name": "A\u2191G(2)",
        "irrep_list": [
          "GM1",
          "GM2",
          "(M)Z1",
          "(M)Z2",
          "(N)L1",
          "(N)L1",
          "(P)H1",
          "(PA)HA1",
          "(X)Y1",
          "(XA)T1"
        ],
        "vector": [
          1.0,
          1.0,
          0.0,
          1.0,
          1.0,
          0.0,
          2.0,
          1.0,
          1.0,
          1.0,
          1.0
        ]
      },
      {
        "wyckoff_position": "4a(4',2)",
        "ebr_name": "BB\u2191G(4)",
        "irrep_list": [
          "GM3GM4",
          "GM3GM4",
          "(M)Z3Z4",
          "(M)Z3Z4",
          "(N)L1",
          "(N)L1",
          "(N)L1",
          "(N)L1",
          "(P)H1",
          "(P)H1",
          "(PA)HA1",
          "(PA)HA1",
          "(X)Y1",
          "(X)Y1",
          "(XA)T1",
          "(XA)T1"
        ],
        "vector": [
          0.0,
          0.0,
          2.0,
          0.0,
          0.0,
          2.0,
          4.0,
          2.0,
          2.0,
          2.0,
          2.0
        ]
      },
      {
        "wyckoff_position": "4b(4',2)",
        "ebr_name": "A\u2191G(2)",
        "irrep_list": [
          "GM1",
          "GM2",
          "(M)Z1",
          "(M)Z2",
          "(N)L1",
          "(N)L1",
          "(P)H1",
          "(PA)HA1",
          "(X)Y1",
          "(XA)T1"
        ],
        "vector": [
          1.0,
          1.0,
          0.0,
          1.0,
          1.0,
          0.0,
          2.0,
          1.0,
          1.0,
          1.0,
          1.0
        ]
      },
      {
        "wyckoff_position": "4b(4',2)",
        "ebr_name": "BB\u2191G(4)",
        "irrep_list": [
          "GM3GM4",
          "GM3GM4",
          "(M)Z3Z4",
          "(M)Z3Z4",
          "(N)L1",
          "(N)L1",
          "(N)L1",
          "(N)L1",
          "(P)H1",
          "(P)H1",
          "(PA)HA1",
          "(PA)HA1",
          "(X)Y1",
          "(X)Y1",
          "(XA)T1",
          "(XA)T1"
        ],
        "vector": [
          0.0,
          0.0,
          2.0,
          0.0,
          0.0,
          2.0,
          4.0,
          2.0,
          2.0,
          2.0,
          2.0
        ]
      },
      {
        "wyckoff_position": "8d(2',1)",
        "ebr_name": "A\u2191G(4)",
        "irrep_list": [
          "GM1",
          "GM2",
          "GM3GM4",
          "(M)Z1",
          "(M)Z2",
          "(M)Z3Z4",
          "(N)L1",
          "(N)L1",
          "(N)L1",
          "(N)L1",
          "(P)H1",
          "(P)H1",
          "(PA)HA1",
          "(PA)HA1",
          "(X)Y1",
          "(X)Y1",
          "(XA)T1",
          "(XA)T1"
        ],
        "vector": [
          1.0,
          1.0,
          1.0,
          1.0,
          1.0,
          1.0,
          4.0,
          2.0,
          2.0,
          2.0,
          2.0
        ]
      }
    ],
    "smith_form": {
      "u": [
        [
          1,
          0,
          0,
          0,
          0,
          0,
          0,
          0,
          0,
          0,
          0
        ],
        [
          0,
          0,
          1,
          0,
          0,
          0,
          0,
          0,
          0,
          0,
          0
        ],
        [
          -1,
          1,
          0,
          0,
          0,
          0,
          0,
          0,
          0,
          0,
          0
        ],
        [
          -1,
          0,
          0,
          1,
          0,
          0,
          0,
          0,
          0,
          0,
          0
        ],
        [
          -1,
          0,
          0,
          0,
          1,
          0,
          0,
          0,
          0,
          0,
          0
        ],
        [
          0,
          0,
          -1,
          0,
          0,
          1,
          0,
          0,
          0,
          0,
          0
        ],
        [
          -2,
          0,
          -2,
          0,
          0,
          0,
          1,
          0,
          0,
          0,
          0
        ],
        [
          -1,
          0,
          -1,
          0,
          0,
          0,
          0,
          1,
          0,
          0,
          0
        ],
        [
          -1,
          0,
          -1,
          0,
          0,
          0,
          0,
          0,
          1,
          0,
          0
        ],
        [
          -1,
          0,
          -1,
          0,
          0,
          0,
          0,
          0,
          0,
          1,
          0
        ],
        [
          -1,
          0,
          -1,
          0,
          0,
          0,
          0,
          0,
          0,
          0,
          1
        ]
      ],
      "r": [
        [
          1,
          0,
          0,
          0,
          0
        ],
        [
          0,
          1,
          0,
          0,
          0
        ],
        [
          0,
          0,
          0,
          0,
          0
        ],
        [
          0,
          0,
          0,
          0,
          0
        ],
        [
          0,
          0,
          0,
          0,
          0
        ],
        [
          0,
          0,
          0,
          0,
          0
        ],
        [
          0,
          0,
          0,
          0,
          0
        ],
        [
          0,
          0,
          0,
          0,
          0
        ],
        [
          0,
          0,
          0,
          0,
          0
        ],
        [
          0,
          0,
          0,
          0,
          0
        ],
        [
          0,
          0,
          0,
          0,
          0
        ]
      ],
      "v": [
        [
          1,
          -1,
          -1,
          0,
          -2
        ],
        [
          0,
          0,
          0,
          -1,
          -1
        ],
        [
          0,
          0,
          1,
          0,
          0
        ],
        [
          0,
          0,
          0,
          1,
          0
        ],
        [
          0,
          1,
          0,
          0,
          2
        ]
      ]
    }
  },
  "double": {
    "basis": {
      "irrep_labels": [
        "-GM5",
        "-(M)Z5",
        "-(N)L2",
        "-(P)H2",
        "-(P)H3",
        "-(P)H4",
        "-(P)H5",
        "-(PA)HA2",
        "-(PA)HA3",
        "-(PA)HA4",
        "-(PA)HA5",
        "-(X)Y2",
        "-(X)Y3",
        "-(X)Y4",
        "-(X)Y5",
        "-(XA)T2",
        "-(XA)T3",
        "-(XA)T4",
        "-(XA)T5"
      ],
      "degeneracies": [
        2,
        2,
        1,
        1,
        1,
        1,
        1,
        1,
        1,
        1,
        1,
        1,
        1,
        1,
        1,
        1,
        1,
        1,
        1
      ]
    },
    "ebrs": [
      {
        "wyckoff_position": "4a(4',2)",
        "ebr_name": "-1E2E\u2191G(4)",
        "irrep_list": [
          "-GM5",
          "-GM5",
          "-(M)Z5",
          "-(M)Z5",
          "-(N)L2",
          "-(N)L2",
          "-(N)L2",
          "-(N)L2",
          "-(P)H2",
          "-(P)H3",
          "-(P)H4",
          "-(P)H5",
          "-(PA)HA2",
          "-(PA)HA3",
          "-(PA)HA4",
          "-(PA)HA5",
          "-(X)Y2",
          "-(X)Y3",
          "-(X)Y4",
          "-(X)Y5",
          "-(XA)T2",
          "-(XA)T3",
          "-(XA)T4",
          "-(XA)T5"
        ],
        "vector": [
          2.0,
          2.0,
          4.0,
          1.0,
          1.0,
          1.0,
          1.0,
          1.0,
          1.0,
          1.0,
          1.0,
          1.0,
          1.0,
          1.0,
          1.0,
          1.0,
          1.0,
          1.0,
          1.0
        ]
      },
      {
        "wyckoff_position": "4b(4',2)",
        "ebr_name": "-1E2E\u2191G(4)",
        "irrep_list": [
          "-GM5",
          "-GM5",
          "-(M)Z5",
          "-(M)Z5",
          "-(N)L2",
          "-(N)L2",
          "-(N)L2",
          "-(N)L2",
          "-(P)H2",
          "-(P)H3",
          "-(P)H4",
          "-(P)H5",
          "-(PA)HA2",
          "-(PA)HA3",
          "-(PA)HA4",
          "-(PA)HA5",
          "-(X)Y2",
          "-(X)Y3",
          "-(X)Y4",
          "-(X)Y5",
          "-(XA)T2",
          "-(XA)T3",
          "-(XA)T4",
          "-(XA)T5"
        ],
        "vector": [
          2.0,
          2.0,
          4.0,
          1.0,
          1.0,
          1.0,
          1.0,
          1.0,
          1.0,
          1.0,
          1.0,
          1.0,
          1.0,
          1.0,
          1.0,
          1.0,
          1.0,
          1.0,
          1.0
        ]
      },
      {
        "wyckoff_position": "8d(2',1)",
        "ebr_name": "-A\u2191G(4)",
        "irrep_list": [
          "-GM5",
          "-GM5",
          "-(M)Z5",
          "-(M)Z5",
          "-(N)L2",
          "-(N)L2",
          "-(N)L2",
          "-(N)L2",
          "-(P)H2",
          "-(P)H3",
          "-(P)H4",
          "-(P)H5",
          "-(PA)HA2",
          "-(PA)HA3",
          "-(PA)HA4",
          "-(PA)HA5",
          "-(X)Y2",
          "-(X)Y3",
          "-(X)Y4",
          "-(X)Y5",
          "-(XA)T2",
          "-(XA)T3",
          "-(XA)T4",
          "-(XA)T5"
        ],
        "vector": [
          2.0,
          2.0,
          4.0,
          1.0,
          1.0,
          1.0,
          1.0,
          1.0,
          1.0,
          1.0,
          1.0,
          1.0,
          1.0,
          1.0,
          1.0,
          1.0,
          1.0,
          1.0,
          1.0
        ]
      }
    ],
    "smith_form": {
      "u": [
        [
          0,
          0,
          0,
          0,
          0,
          0,
          0,
          0,
          0,
          0,
          0,
          0,
          0,
          0,
          0,
          0,
          0,
          0,
          1
        ],
        [
          -1,
          1,
          0,
          0,
          0,
          0,
          0,
          0,
          0,
          0,
          0,
          0,
          0,
          0,
          0,
          0,
          0,
          0,
          0
        ],
        [
          -2,
          0,
          1,
          0,
          0,
          0,
          0,
          0,
          0,
          0,
          0,
          0,
          0,
          0,
          0,
          0,
          0,
          0,
          0
        ],
        [
          -1,
          0,
          0,
          1,
          0,
          0,
          0,
          0,
          0,
          0,
          0,
          0,
          0,
          0,
          0,
          0,
          0,
          0,
          1
        ],
        [
          -1,
          0,
          0,
          0,
          1,
          0,
          0,
          0,
          0,
          0,
          0,
          0,
          0,
          0,
          0,
          0,
          0,
          0,
          1
        ],
        [
          -1,
          0,
          0,
          0,
          0,
          1,
          0,
          0,
          0,
          0,
          0,
          0,
          0,
          0,
          0,
          0,
          0,
          0,
          1
        ],
        [
          -1,
          0,
          0,
          0,
          0,
          0,
          1,
          0,
          0,
          0,
          0,
          0,
          0,
          0,
          0,
          0,
          0,
          0,
          1
        ],
        [
          -1,
          0,
          0,
          0,
          0,
          0,
          0,
          1,
          0,
          0,
          0,
          0,
          0,
          0,
          0,
          0,
          0,
          0,
          1
        ],
        [
          -1,
          0,
          0,
          0,
          0,
          0,
          0,
          0,
          1,
          0,
          0,
          0,
          0,
          0,
          0,
          0,
          0,
          0,
          1
        ],
        [
          -1,
          0,
          0,
          0,
          0,
          0,
          0,
          0,
          0,
          1,
          0,
          0,
          0,
          0,
          0,
          0,
          0,
          0,
          1
        ],
        [
          -1,
          0,
          0,
          0,
          0,
          0,
          0,
          0,
          0,
          0,
          1,
          0,
          0,
          0,
          0,
          0,
          0,
          0,
          1
        ],
        [
          -1,
          0,
          0,
          0,
          0,
          0,
          0,
          0,
          0,
          0,
          0,
          1,
          0,
          0,
          0,
          0,
          0,
          0,
          1
        ],
        [
          -1,
          0,
          0,
          0,
          0,
          0,
          0,
          0,
          0,
          0,
          0,
          0,
          1,
          0,
          0,
          0,
          0,
          0,
          1
        ],
        [
          -1,
          0,
          0,
          0,
          0,
          0,
          0,
          0,
          0,
          0,
          0,
          0,
          0,
          1,
          0,
          0,
          0,
          0,
          1
        ],
        [
          -1,
          0,
          0,
          0,
          0,
          0,
          0,
          0,
          0,
          0,
          0,
          0,
          0,
          0,
          1,
          0,
          0,
          0,
          1
        ],
        [
          -1,
          0,
          0,
          0,
          0,
          0,
          0,
          0,
          0,
          0,
          0,
          0,
          0,
          0,
          0,
          1,
          0,
          0,
          1
        ],
        [
          -1,
          0,
          0,
          0,
          0,
          0,
          0,
          0,
          0,
          0,
          0,
          0,
          0,
          0,
          0,
          0,
          1,
          0,
          1
        ],
        [
          -1,
          0,
          0,
          0,
          0,
          0,
          0,
          0,
          0,
          0,
          0,
          0,
          0,
          0,
          0,
          0,
          0,
          1,
          1
        ],
        [
          -1,
          0,
          0,
          0,
          0,
          0,
          0,
          0,
          0,
          0,
          0,
          0,
          0,
          0,
          0,
          0,
          0,
          0,
          2
        ]
      ],
      "r": [
        [
          1,
          0,
          0
        ],
        [
          0,
          0,
          0
        ],
        [
          0,
          0,
          0
        ],
        [
          0,
          0,
          0
        ],
        [
          0,
          0,
          0
        ],
        [
          0,
          0,
          0
        ],
        [
          0,
          0,
          0
        ],
        [
          0,
          0,
          0
        ],
        [
          0,
          0,
          0
        ],
        [
          0,
          0,
          0
        ],
        [
          0,
          0,
          0
        ],
        [
          0,
          0,
          0
        ],
        [
          0,
          0,
          0
        ],
        [
          0,
          0,
          0
        ],
        [
          0,
          0,
          0
        ],
        [
          0,
          0,
          0
        ],
        [
          0,
          0,
          0
        ],
        [
          0,
          0,
          0
        ],
        [
          0,
          0,
          0
        ]
      ],
      "v": [
        [
          1,
          -1,
          -1
        ],
        [
          0,
          1,
          0
        ],
        [
          0,
          0,
          1
        ]
      ]
    }
  }
}