{
  "single": {
    "basis": {
      "irrep_labels": [
        "GM1",
        "GM2",
        "GM3",
        "GM4",
        "R1R2",
        "S1S2",
        "T1T2",
        "W1W1",
        "WA1WA1",
        "X1",
        "X2",
        "X3",
        "X4"
      ],
      "degeneracies": [
        1,
        1,
        1,
        1,
        2,
        2,
        2,
        4,
        4,
        1,
        1,
        1,
        1
      ]
    },
    "ebrs": [
      {
        "wyckoff_position": "8a(1',1)",
        "ebr_name": "A\u2191G(4)",
        "irrep_list": [
          "GM1",
          "GM2",
          "GM3",
          "GM4",
          "R1R2",
          "R1R2",
          "S1S2",
          "S1S2",
          "T1T2",
          "T1T2",
          "W1W1",
          "WA1WA1",
          "X1",
          "X2",
          "X3",
          "X4"
        ],
        "vector": [
          1.0,
          1.0,
          1.0,
          1.0,
          2.0,
          2.0,
          2.0,
          1.0,
          1.0,
          1.0,
          1.0,
          1.0,
          1.0
        ]
      },
      {
        "wyckoff_position": "8b(1',1)",
        "ebr_name": "A\u2191G(4)",
        "irrep_list": [
          "GM1",
          "GM2",
          "GM3",
          "GM4",
          "R1R2",
          "R1R2",
          "S1S2",
          "S1S2",
          "T1T2",
          "T1T2",
          "W1W1",
          "WA1WA1",
          "X1",
          "X2",
          "X3",
          "X4"
        ],
        "vector": [
          1.0,
          1.0,
          1.0,
          1.0,
          2.0,
          2.0,
          2.0,
          1.0,
          1.0,
          1.0,
          1.0,
          1.0,
          1.0
        ]
      },
      {
        "wyckoff_position": "8c(2,2)",
        "ebr_name": "A\u2191G(4)",
        "irrep_list": [
          "GM1",
          "GM1",
          "GM3",
          "GM3",
          "R1R2",
          "R1R2",
          "S1S2",
          "S1S2",
          "T1T2",
          "T1T2",
          "W1W1",
          "WA1WA1",
          "X1",
          "X1",
          "X3",
          "X3"
        ],
        "vector": [
          2.0,
          0.0,
          2.0,
          0.0,
          2.0,
          2.0,
          2.0,
          1.0,
          1.0,
          2.0,
          0.0,
          2.0,
          0.0
        ]
      },
      {
        "wyckoff_position": "8c(2,2)",
        "ebr_name": "B\u2191G(4)",
        "irrep_list": [
          "GM2",
          "GM2",
          "GM4",
          "GM4",
          "R1R2",
          "R1R2",
          "S1S2",
          "S1S2",
          "T1T2",
          "T1T2",
          "W1W1",
          "WA1WA1",
          "X2",
          "X2",
          "X4",
          "X4"
        ],
        "vector": [
          0.0,
          2.0,
          0.0,
          2.0,
          2.0,
          2.0,
          2.0,
          1.0,
          1.0,
          0.0,
          2.0,
          0.0,
          2.0
        ]
      },
      {
        "wyckoff_position": "8d(2,2)",
        "ebr_name": "A\u2191G(4)",
        "irrep_list": [
          "GM1",
          "GM1",
          "GM4",
          "GM4",
          "R1R2",
          "R1R2",
          "S1S2",
          "S1S2",
          "T1T2",
          "T1T2",
          "W1W1",
          "WA1WA1",
          "X2",
          "X2",
          "X3",
          "X3"
        ],
        "vector": [
          2.0,
          0.0,
          0.0,
          2.0,
          2.0,
          2.0,
          2.0,
          1.0,
          1.0,
          0.0,
          2.0,
          2.0,
          0.0
        ]
      },
      {
        "wyckoff_position": "8d(2,2)",
        "ebr_name": "B\u2191G(4)",
        "irrep_list": [
          "GM2",
          "GM2",
          "GM3",
          "GM3",
          "R1R2",
          "R1R2",
          "S1S2",
          "S1S2",
          "T1T2",
          "T1T2",
          "W1W1",
          "WA1WA1",
          "X1",
          "X1",
          "X4",
          "X4"
        ],
        "vector": [
          0.0,
          2.0,
          2.0,
          0.0,
          2.0,
          2.0,
          2.0,
          1.0,
          1.0,
          2.0,
          0.0,
          0.0,
          2.0
        ]
      },
      {
        "wyckoff_position": "8e(2,2)",
        "ebr_name": "A\u2191G(4)",
        "irrep_list": [
          "GM1",
          "GM1",
          "GM2",
          "GM2",
          "R1R2",
          "R1R2",
          "S1S2",
          "S1S2",
          "T1T2",
          "T1T2",
          "W1W1",
          "WA1WA1",
          "X1",
          "X1",
          "X2",
          "X2"
        ],
        "vector": [
          2.0,
          2.0,
          0.0,
          0.0,
          2.0,
          2.0,
          2.0,
          1.0,
          1.0,
          2.0,
          2.0,
          0.0,
          0.0
        ]
      },
      {
        "wyckoff_position": "8e(2,2)",
        "ebr_name": "B\u2191G(4)",
        "irrep_list": [
          "GM3",
          "GM3",
          "GM4",
          "GM4",
          "R1R2",
          "R1R2",
          "S1S2",
          "S1S2",
          "T1T2",
          "T1T2",
          "W1W1",
          "WA1WA1",
          "X3",
          "X3",
          "X4",
          "X4"
        ],
        "vector": [
          0.0,
          0.0,
          2.0,
          2.0,
          2.0,
          2.0,
          2.0,
          1.0,
          1.0,
          0.0,
          0.0,
          2.0,
          2.0
        ]
      }
    ],
    "smith_form": {
      "u": [
        [
          -1,
          0,
          0,
          1,
          0,
          0,
          0,
          0,
          0,
          1,
          0,
          0,
          0
        ],
        [
          1,
          0,
          0,
          -1,
          0,
          0,
          0,
          0,
          1,
          -1,
          0,
          0,
          0
        ],
        [
          1,
          0,
          0,
          0,
          0,
          0,
          0,
          0,
          0,
          -1,
          0,
          0,
          0
        ],
        [
          0,
          0,
          0,
          -1,
          0,
          0,
          0,
          0,
          0,
          0,
          1,
          0,
          0
        ],
        [
          0,
          0,
          0,
          -1,
          1,
          0,
          0,
          0,
          0,
          -1,
          0,
          0,
          0
        ],
        [
          0,
          0,
          0,
          -1,
          0,
          1,
          0,
          0,
          0,
          -1,
          0,
          0,
          0
        ],
        [
          0,
          0,
          0,
          -1,
          0,
          0,
          1,
          0,
          0,
          -1,
          0,
          0,
          0
        ],
        [
          0,
          0,
          0,
          -1,
          0,
          0,
          0,
          1,
          1,
          -1,
          0,
          0,
          0
        ],
        [
          0,
          0,
          0,
          -1,
          0,
          0,
          0,
          0,
          2,
          -1,
          0,
          0,
          0
        ],
        [
          0,
          0,
          1,
          -1,
          0,
          0,
          0,
          0,
          0,
          -1,
          1,
          0,
          0
        ],
        [
          1,
          1,
          0,
          0,
          0,
          0,
          0,
          0,
          0,
          -1,
          -1,
          0,
          0
        ],
        [
          -1,
          0,
          0,
          -1,
          0,
          0,
          0,
          0,
          0,
          0,
          1,
          1,
          0
        ],
        [
          1,
          0,
          0,
          -1,
          0,
          0,
          0,
          0,
          0,
          -1,
          0,
          0,
          1
        ]
      ],
      "r": [
        [
          1,
          0,
          0,
          0,
          0,
          0,
          0,
          0
        ],
        [
          0,
          1,
          0,
          0,
          0,
          0,
          0,
          0
        ],
        [
          0,
          0,
          2,
          0,
          0,
          0,
          0,
          0
        ],
        [
          0,
          0,
          0,
          2,
          0,
          0,
          0,
          0
        ],
        [
          0,
          0,
          0,
          0,
          0,
          0,
          0,
          0
        ],
        [
          0,
          0,
          0,
          0,
          0,
          0,
          0,
          0
        ],
        [
          0,
          0,
          0,
          0,
          0,
          0,
          0,
          0
        ],
        [
          0,
          0,
          0,
          0,
          0,
          0,
          0,
          0
        ],
        [
          0,
          0,
          0,
          0,
          0,
          0,
          0,
          0
        ],
        [
          0,
          0,
          0,
          0,
          0,
          0,
          0,
          0
        ],
        [
          0,
          0,
          0,
          0,
          0,
          0,
          0,
          0
        ],
        [
          0,
          0,
          0,
          0,
          0,
          0,
          0,
          0
        ],
        [
          0,
          0,
          0,
          0,
          0,
          0,
          0,
          0
        ]
      ],
      "v": [
        [
          1,
          0,
          0,
          0,
          -1,
          -2,
          -2,
          -2
        ],
        [
          0,
          0,
          0,
          0,
          1,
          0,
          0,
          0
        ],
        [
          0,
          1,
          -1,
          -1,
          0,
          0,
          1,
          0
        ],
        [
          0,
          0,
          0,
          0,
          0,
          0,
          1,
          0
        ],
        [
          0,
          0,
          1,
          0,
          0,
          1,
          0,
          0
        ],
        [
          0,
          0,
          0,
          0,
          0,
          1,
          0,
          0
        ],
        [
          0,
          0,
          0,
          1,
          0,
          0,
          0,
          1
        ],
        [
          0,
          0,
          0,
          0,
          0,
          0,
          0,
          1
        ]
      ]
    }
  },
  "double": {
    "basis": {
      "irrep_labels": [
        "-GM5",
        "-R3R3",
        "-R4R4",
        "-S3S3",
        "-S4S4",
        "-T3T3",
        "-T4T4",
        "-W2W2",
        "-W3W3",
        "-W4W4",
        "-W5W5",
        "-WA2WA2",
        "-WA3WA3",
        "-WA4WA4",
        "-WA5WA5",
        "-X5"
      ],
      "degeneracies": [
        2,
        2,
        2,
        2,
        2,
        2,
        2,
        2,
        2,
        2,
        2,
        2,
        2,
        2,
        2,
        2
      ]
    },
    "ebrs": [
      {
        "wyckoff_position": "8c(2,2)",
        "ebr_name": "-1E\u2191G(4)",
        "irrep_list": [
          "-GM5",
          "-GM5",
          "-R3R3",
          "-R4R4",
          "-S4S4",
          "-S4S4",
          "-T3T3",
          "-T4T4",
          "-W4W4",
          "-W5W5",
          "-WA2WA2",
          "-WA3WA3",
          "-X5",
          "-X5"
        ],
        "vector": [
          2.0,
          1.0,
          1.0,
          0.0,
          2.0,
          1.0,
          1.0,
          0.0,
          0.0,
          1.0,
          1.0,
          1.0,
          1.0,
          0.0,
          0.0,
          2.0
        ]
      },
      {
        "wyckoff_position": "8c(2,2)",
        "ebr_name": "-2E\u2191G(4)",
        "irrep_list": [
          "-GM5",
          "-GM5",
          "-R3R3",
          "-R4R4",
          "-S3S3",
          "-S3S3",
          "-T3T3",
          "-T4T4",
          "-W2W2",
          "-W3W3",
          "-WA4WA4",
          "-WA5WA5",
          "-X5",
          "-X5"
        ],
        "vector": [
          2.0,
          1.0,
          1.0,
          2.0,
          0.0,
          1.0,
          1.0,
          1.0,
          1.0,
          0.0,
          0.0,
          0.0,
          0.0,
          1.0,
          1.0,
          2.0
        ]
      },
      {
        "wyckoff_position": "8d(2,2)",
        "ebr_name": "-1E\u2191G(4)",
        "irrep_list": [
          "-GM5",
          "-GM5",
          "-R4R4",
          "-R4R4",
          "-S3S3",
          "-S4S4",
          "-T3T3",
          "-T4T4",
          "-W2W2",
          "-W5W5",
          "-WA3WA3",
          "-WA4WA4",
          "-X5",
          "-X5"
        ],
        "vector": [
          2.0,
          0.0,
          2.0,
          1.0,
          1.0,
          1.0,
          1.0,
          1.0,
          0.0,
          0.0,
          1.0,
          0.0,
          1.0,
          1.0,
          0.0,
          2.0
        ]
      },
      {
        "wyckoff_position": "8d(2,2)",
        "ebr_name": "-2E\u2191G(4)",
        "irrep_list": [
          "-GM5",
          "-GM5",
          "-R3R3",
          "-R3R3",
          "-S3S3",
          "-S4S4",
          "-T3T3",
          "-T4T4",
          "-W3W3",
          "-W4W4",
          "-WA2WA2",
          "-WA5WA5",
          "-X5",
          "-X5"
        ],
        "vector": [
          2.0,
          2.0,
          0.0,
          1.0,
          1.0,
          1.0,
          1.0,
          0.0,
          1.0,
          1.0,
          0.0,
          1.0,
          0.0,
          0.0,
          1.0,
          2.0
        ]
      },
      {
        "wyckoff_position": "8e(2,2)",
        "ebr_name": "-1E\u2191G(4)",
        "irrep_list": [
          "-GM5",
          "-GM5",
          "-R3R3",
          "-R4R4",
          "-S3S3",
          "-S4S4",
          "-T4T4",
          "-T4T4",
          "-W3W3",
          "-W5W5",
          "-WA2WA2",
          "-WA4WA4",
          "-X5",
          "-X5"
        ],
        "vector": [
          2.0,
          1.0,
          1.0,
          1.0,
          1.0,
          0.0,
          2.0,
          0.0,
          1.0,
          0.0,
          1.0,
          1.0,
          0.0,
          1.0,
          0.0,
          2.0
        ]
      },
      {
        "wyckoff_position": "8e(2,2)",
        "ebr_name": "-2E\u2191G(4)",
        "irrep_list": [
          "-GM5",
          "-GM5",
          "-R3R3",
          "-R4R4",
          "-S3S3",
          "-S4S4",
          "-T3T3",
          "-T3T3",
          "-W2W2",
          "-W4W4",
          "-WA3WA3",
          "-WA5WA5",
          "-X5",
          "-X5"
        ],
        "vector": [
          2.0,
          1.0,
          1.0,
          1.0,
          1.0,
          2.0,
          0.0,
          1.0,
          0.0,
          1.0,
          0.0,
          0.0,
          1.0,
          0.0,
          1.0,
          2.0
        ]
      }
    ],
    "smith_form": {
      "u": [
        [
          0,
          0,
          0,
          0,
          0,
          0,
          0,
          0,
          0,
          1,
          0,
          0,
          0,
          0,
          0,
          0
        ],
        [
          0,
          0,
          0,
          0,
          0,
          0,
          0,
          0,
          0,
          0,
          0,
          0,
          0,
          0,
          1,
          0
        ],
        [
          0,
          0,
          1,
          -1,
          0,
          0,
          0,
          0,
          0,
          -1,
          0,
          0,
          0,
          0,
          1,
          0
        ],
        [
          0,
          2,
          1,
          -2,
          0,
          0,
          0,
          0,
          0,
          -3,
          0,
          0,
          0,
          0,
          1,
          0
        ],
        [
          0,
          -1,
          -1,
          1,
          1,
          0,
          0,
          0,
          0,
          0,
          0,
          0,
          0,
          0,
          0,
          0
        ],
        [
          0,
          1,
          0,
          -1,
          0,
          1,
          0,
          0,
          0,
          -2,
          0,
          0,
          0,
          0,
          0,
          0
        ],
        [
          0,
          -2,
          -1,
          1,
          0,
          0,
          1,
          0,
          0,
          2,
          0,
          0,
          0,
          0,
          0,
          0
        ],
        [
          0,
          1,
          0,
          -1,
          0,
          0,
          0,
          1,
          0,
          -1,
          0,
          0,
          0,
          0,
          0,
          0
        ],
        [
          0,
          -1,
          0,
          0,
          0,
          0,
          0,
          0,
          1,
          1,
          0,
          0,
          0,
          0,
          0,
          0
        ],
        [
          1,
          -1,
          -1,
          0,
          0,
          0,
          0,
          0,
          0,
          0,
          0,
          0,
          0,
          0,
          0,
          0
        ],
        [
          0,
          -1,
          -1,
          1,
          0,
          0,
          0,
          0,
          0,
          1,
          1,
          0,
          0,
          0,
          0,
          0
        ],
        [
          0,
          -1,
          0,
          0,
          0,
          0,
          0,
          0,
          0,
          0,
          0,
          1,
          0,
          0,
          1,
          0
        ],
        [
          0,
          1,
          0,
          -1,
          0,
          0,
          0,
          0,
          0,
          -2,
          0,
          0,
          1,
          0,
          1,
          0
        ],
        [
          0,
          0,
          0,
          -1,
          0,
          0,
          0,
          0,
          0,
          0,
          0,
          0,
          0,
          1,
          1,
          0
        ],
        [
          0,
          1,
          1,
          -2,
          0,
          0,
          0,
          0,
          0,
          -2,
          0,
          0,
          0,
          0,
          2,
          0
        ],
        [
          0,
          -1,
          -1,
          0,
          0,
          0,
          0,
          0,
          0,
          0,
          0,
          0,
          0,
          0,
          0,
          1
        ]
      ],
      "r": [
        [
          1,
          0,
          0,
          0,
          0,
          0
        ],
        [
          0,
          1,
          0,
          0,
          0,
          0
        ],
        [
          0,
          0,
          1,
          0,
          0,
          0
        ],
        [
          0,
          0,
          0,
          1,
          0,
          0
        ],
        [
          0,
          0,
          0,
          0,
          0,
          0
        ],
        [
          0,
          0,
          0,
          0,
          0,
          0
        ],
        [
          0,
          0,
          0,
          0,
          0,
          0
        ],
        [
          0,
          0,
          0,
          0,
          0,
          0
        ],
        [
          0,
          0,
          0,
          0,
          0,
          0
        ],
        [
          0,
          0,
          0,
          0,
          0,
          0
        ],
        [
          0,
          0,
          0,
          0,
          0,
          0
        ],
        [
          0,
          0,
          0,
          0,
          0,
          0
        ],
        [
          0,
          0,
          0,
          0,
          0,
          0
        ],
        [
          0,
          0,
          0,
          0,
          0,
          0
        ],
        [
          0,
          0,
          0,
          0,
          0,
          0
        ],
        [
          0,
          0,
          0,
          0,
          0,
          0
        ]
      ],
      "v": [
        [
          1,
          0,
          0,
          0,
          -1,
          -1
        ],
        [
          0,
          1,
          0,
          0,
          -1,
          -1
        ],
        [
          0,
          0,
          1,
          0,
          1,
          0
        ],
        [
          0,
          0,
          0,
          0,
          1,
          0
        ],
        [
          0,
          0,
          0,
          1,
          0,
          1
        ],
        [
          0,
          0,
          0,
          0,
          0,
          1
        ]
      ]
    }
  }
}