{
  "single": {
    "basis": {
      "irrep_labels": [
        "GM1",
        "(A)Z1Z1",
        "(L)U1",
        "(LA)T1",
        "(M)R1R1",
        "(V)X1",
        "(VA)Y1",
        "(Y)V1"
      ],
      "degeneracies": [
        1,
        2,
        1,
        1,
        2,
        1,
        1,
        1
      ]
    },
    "ebrs": [
      {
        "wyckoff_position": "4a(1,1)",
        "ebr_name": "A\u2191G(2)",
        "irrep_list": [
          "GM1",
          "GM1",
          "(A)Z1Z1",
          "(L)U1",
          "(L)U1",
          "(LA)T1",
          "(LA)T1",
          "(M)R1R1",
          "(V)X1",
          "(V)X1",
          "(VA)Y1",
          "(VA)Y1",
          "(Y)V1",
          "(Y)V1"
        ],
        "vector": [
          2.0,
          1.0,
          2.0,
          2.0,
          1.0,
          2.0,
          2.0,
          2.0
        ]
      }
    ],
    "smith_form": {
      "u": [
        [
          0,
          0,
          0,
          0,
          1,
          0,
          0,
          0
        ],
        [
          -1,
          1,
          0,
          0,
          1,
          0,
          0,
          0
        ],
        [
          -1,
          0,
          1,
          0,
          0,
          0,
          0,
          0
        ],
        [
          -1,
          0,
          0,
          1,
          0,
          0,
          0,
          0
        ],
        [
          -1,
          0,
          0,
          0,
          2,
          0,
          0,
          0
        ],
        [
          -1,
          0,
          0,
          0,
          0,
          1,
          0,
          0
        ],
        [
          -1,
          0,
          0,
          0,
          0,
          0,
          1,
          0
        ],
        [
          -1,
          0,
          0,
          0,
          0,
          0,
          0,
          1
        ]
      ],
      "r": [
        1,
        0,
        0,
        0,
        0,
        0,
        0,
        0
      ],
      "v": 1
    }
  },
  "double": {
    "basis": {
      "irrep_labels": [
        "-GM2",
        "-(A)Z2Z2",
        "-(L)U2",
        "-(LA)T2",
        "-(M)R2R2",
        "-(V)X2",
        "-(VA)Y2",
        "-(Y)V2"
      ],
      "degeneracies": [
        1,
        2,
        1,
        1,
        2,
        1,
        1,
        1
      ]
    },
    "ebrs": [
      {
        "wyckoff_position": "4a(1,1)",
        "ebr_name": "-A\u2191G(2)",
        "irrep_list": [
          "-GM2",
          "-GM2",
          "-(A)Z2Z2",
          "-(L)U2",
          "-(L)U2",
          "-(LA)T2",
          "-(LA)T2",
          "-(M)R2R2",
          "-(V)X2",
          "-(V)X2",
          "-(VA)Y2",
          "-(VA)Y2",
          "-(Y)V2",
          "-(Y)V2"
        ],
        "vector": [
          2.0,
          1.0,
          2.0,
          2.0,
          1.0,
          2.0,
          2.0,
          2.0
        ]
      }
    ],
    "smith_form": {
      "u": [
        [
          0,
          0,
          0,
          0,
          1,
          0,
          0,
          0
        ],
        [
          -1,
          1,
          0,
          0,
          1,
          0,
          0,
          0
        ],
        [
          -1,
          0,
          1,
          0,
          0,
          0,
          0,
          0
        ],
        [
          -1,
          0,
          0,
          1,
          0,
          0,
          0,
          0
        ],
        [
          -1,
          0,
          0,
          0,
          2,
          0,
          0,
          0
        ],
        [
          -1,
          0,
          0,
          0,
          0,
          1,
          0,
          0
        ],
        [
          -1,
          0,
          0,
          0,
          0,
          0,
          1,
          0
        ],
        [
          -1,
          0,
          0,
          0,
          0,
          0,
          0,
          1
        ]
      ],
      "r": [
        1,
        0,
        0,
        0,
        0,
        0,
        0,
        0
      ],
      "v": 1
    }
  }
}